lzsr_password/__init__.py
lzsr_password/lzsr_key.py
lzsr_password/lzsr_lock.py
lzsr_password/setup.py
lzsr_password-1.1.0.dist-info/LICENSE
lzsr_password-1.1.0.dist-info/METADATA
lzsr_password-1.1.0.dist-info/WHEEL
lzsr_password-1.1.0.dist-info/top_level.txt
lzsr_password-1.1.0.dist-info/RECORD
